flowkit/__init__.py
flowkit/utils.py
flowkit/models/__init__.py
flowkit/models/gate.py
flowkit/models/sample.py
flowkit/models/transforms/__init__.py
flowkit/models/transforms/base_transform.py
flowkit/models/transforms/gml_transforms.py
flowkit/models/transforms/transforms.py
flowkit/resources/DataTypes.v2.0.xsd
flowkit/resources/Gating-ML.v2.0.xsd
flowkit/resources/Transformations.v2.0.xsd
flowkit/resources/__init__.py
unit_test/__init__.py
unit_test/gating_unit_tests.py
unit_test/sample_unit_tests.py
unit_test/unit_tests.py
FlowKit-0.1.0.dist-info/LICENSE
FlowKit-0.1.0.dist-info/METADATA
FlowKit-0.1.0.dist-info/WHEEL
FlowKit-0.1.0.dist-info/top_level.txt
FlowKit-0.1.0.dist-info/RECORD
