Metadata-Version: 2.1
Name: FlowKit
Version: 0.1.0
Summary: Flow Cytometry Toolkit
Home-page: https://github.com/whitews/flowkit
Author: Scott White
License: BSD
Platform: UNKNOWN
Requires-Dist: flowio
Requires-Dist: flowutils
Requires-Dist: matplotlib
Requires-Dist: scipy
Requires-Dist: seaborn
Requires-Dist: pandas
Requires-Dist: numpy
Requires-Dist: lxml
Requires-Dist: bokeh
Requires-Dist: anytree
